[{"id":"node2297","bookName":"Инферно","price":299,"author":"Дэн Браун","year":null,"score":{"1":21,"2":16,"3":47,"4":61,"5":288},"avgScore":4.3372,"artScore":26.329897120303798,"link":"http://www.litres.ru/den-braun/inferno/","thumbnail":"http://cv2.litres.ru/static/bookimages/08/32/81/08328126.bin.dir/08328126.cover_89.jpg"},{"id":"node2373","bookName":"Космоэколухи","price":89.9,"author":"Ольга Громыко","year":null,"score":{"1":4,"2":3,"3":4,"4":25,"5":213},"avgScore":4.7671,"artScore":26.302074650508857,"link":"http://www.litres.ru/olga-gromyko/kosmoekoluhi/","thumbnail":"http://cv5.litres.ru/static/bookimages/05/80/01/05800155.bin.dir/05800155.cover_89.jpg"},{"id":"node2376","bookName":"Девятый","price":89.9,"author":"Артем Каменистый","year":null,"score":{"1":5,"2":4,"3":12,"4":46,"5":183},"avgScore":4.592,"artScore":25.354548534823433,"link":"http://www.litres.ru/artem-kamenistyy/devyatyy/","thumbnail":"http://cv5.litres.ru/static/bookimages/04/42/57/04425755.bin.dir/04425755.cover_89.jpg"},{"id":"node2369","bookName":"Умри красиво","price":129.9,"author":"Сергей Тармашев","year":null,"score":{"1":7,"2":3,"3":7,"4":16,"5":181},"avgScore":4.6869,"artScore":25.14987823406686,"link":"http://www.litres.ru/sergey-tarmashev/umri-krasivo/","thumbnail":"http://cv4.litres.ru/static/bookimages/08/55/72/08557243.bin.dir/08557243.cover_89.jpg"},{"id":"node2320","bookName":"Трудно быть богом","price":59.9,"author":"Аркадий и Борис Стругацкие","year":null,"score":{"1":9,"2":2,"3":6,"4":21,"5":177},"avgScore":4.6512,"artScore":24.979711754986358,"link":"http://www.litres.ru/arkadiy-i-boris-strugackie/trudno-byt-bogom/","thumbnail":"http://cv5.litres.ru/static/bookimages/09/02/01/09020152.bin.dir/09020152.cover_89.jpg"},{"id":"node2311","bookName":"11/22/63","price":199,"author":"Стивен Кинг","year":null,"score":{"1":4,"2":7,"3":18,"4":30,"5":171},"avgScore":4.5522,"artScore":24.75508276690524,"link":"http://www.litres.ru/stiven-king/11-22-63/","thumbnail":"http://cv2.litres.ru/static/bookimages/07/09/97/07099722.bin.dir/07099722.cover_89.jpg"},{"id":"node2315","bookName":"Космобиолухи","price":89.9,"author":"Ольга Громыко и др.","year":null,"score":{"1":5,"2":6,"3":15,"4":43,"5":165},"avgScore":4.5256,"artScore":24.68882504421157,"link":"http://www.litres.ru/andrey-ulanov/olga-gromyko/kosmobioluhi/","thumbnail":"http://cv3.litres.ru/static/bookimages/05/80/01/05800135.bin.dir/05800135.cover_89.jpg"},{"id":"node3498","bookName":"Принцесса стоит смерти","price":null,"author":"Сергей Лукьяненко","year":null,"score":{"1":13,"2":7,"3":12,"4":29,"5":184},"avgScore":4.4857,"artScore":24.677072540514022,"link":"http://www.litres.ru/sergey-lukyanenko/princessa-stoit-smerti/","thumbnail":"http://cv6.litres.ru/static/bookimages/00/13/36/00133669.bin.dir/00133669.cover_89.jpg"},{"id":"node2365","bookName":"Леди не движется","price":99.9,"author":"Олег Дивов","year":null,"score":{"1":4,"2":12,"3":13,"4":29,"5":166},"avgScore":4.5223,"artScore":24.473202901055643,"link":"http://www.litres.ru/oleg-divov/ledi-ne-dvizhetsya/","thumbnail":"http://cv5.litres.ru/static/bookimages/08/13/05/08130554.bin.dir/08130554.cover_89.jpg"},{"id":"node2405","bookName":"Барлиона","price":69.9,"author":"Василий Маханенко","year":null,"score":{"1":1,"2":2,"3":3,"4":12,"5":134},"avgScore":4.8158,"artScore":24.193950925901255,"link":"http://www.litres.ru/vasiliy-mahanenko/barliona/","thumbnail":"http://cv1.litres.ru/static/bookimages/07/99/66/07996617.bin.dir/07996617.cover_89.jpg"},{"id":"node2372","bookName":"Игра Эндера","price":119.9,"author":"Орсон Скотт Кард","year":null,"score":{"1":11,"2":5,"3":15,"4":23,"5":165},"avgScore":4.4886,"artScore":24.189303695726668,"link":"http://www.litres.ru/orson-kard/igra-endera/","thumbnail":"http://cv5.litres.ru/static/bookimages/10/54/39/10543958.bin.dir/10543958.cover_89.jpg"},{"id":"node2381","bookName":"Землянин","price":149.9,"author":"Роман Злотников","year":null,"score":{"1":4,"2":11,"3":11,"4":51,"5":148},"avgScore":4.4578,"artScore":24.14377201094763,"link":"http://www.litres.ru/roman-zlotnikov/zemlyanin/","thumbnail":"http://cv4.litres.ru/static/bookimages/06/68/09/06680943.bin.dir/06680943.cover_89.jpg"},{"id":"node2299","bookName":"Космопсихолухи. Том 1","price":99.9,"author":"Ольга Громыко","year":null,"score":{"1":6,"2":2,"3":3,"4":18,"5":143},"avgScore":4.686,"artScore":24.12139853346345,"link":"http://www.litres.ru/olga-gromyko/kosmopsiholuhi-tom/","thumbnail":"http://cv1.litres.ru/static/bookimages/09/23/41/09234112.bin.dir/09234112.cover_89.jpg"},{"id":"node2612","bookName":"Генерал-адмирал","price":119,"author":"Роман Злотников","year":null,"score":{"1":4,"2":3,"3":6,"4":32,"5":139},"avgScore":4.625,"artScore":24.11907787894156,"link":"http://www.litres.ru/roman-zlotnikov/general-admiral/","thumbnail":"http://cv1.litres.ru/static/bookimages/07/10/02/07100217.bin.dir/07100217.cover_89.jpg"},{"id":"node2385","bookName":"На руинах Мальрока","price":89.9,"author":"Артем Каменистый","year":null,"score":{"1":1,"2":4,"3":11,"4":34,"5":136},"avgScore":4.6129,"artScore":24.105863684204653,"link":"http://www.litres.ru/artem-kamenistyy/na-ruinah-malroka/","thumbnail":"http://cv3.litres.ru/static/bookimages/04/42/80/04428035.bin.dir/04428035.cover_89.jpg"},{"id":"node2460","bookName":"Ветер над островами","price":119,"author":"Андрей Круз","year":null,"score":{"1":0,"2":5,"3":9,"4":28,"5":135},"avgScore":4.6554,"artScore":24.096877847773612,"link":"http://www.litres.ru/andrey-kruz/veter-nad-ostrovami/","thumbnail":"http://cv2.litres.ru/static/bookimages/11/47/11/11471125.bin.dir/11471125.cover_89.jpg"},{"id":"node2462","bookName":"Будущее","price":189.9,"author":"Дмитрий Глуховский","year":null,"score":{"1":34,"2":17,"3":33,"4":42,"5":214},"avgScore":4.1324,"artScore":24.0872605658606,"link":"http://www.litres.ru/dmitriy-gluhovskiy/buduschee/","thumbnail":"http://cv0.litres.ru/static/bookimages/08/32/81/08328106.bin.dir/08328106.cover_89.jpg"},{"id":"node2394","bookName":"Дом на перекрестке","price":99.9,"author":"Милена Завойчинская","year":null,"score":{"1":0,"2":3,"3":4,"4":17,"5":130},"avgScore":4.7792,"artScore":24.072708540293345,"link":"http://www.litres.ru/milena-zavoychinskaya/dom-na-perekrestke-2/","thumbnail":"http://cv6.litres.ru/static/bookimages/08/89/98/08899860.bin.dir/08899860.cover_89.jpg"},{"id":"node2347","bookName":"Один в поле не воин","price":209,"author":"Сергей Тармашев","year":null,"score":{"1":10,"2":2,"3":6,"4":15,"5":149},"avgScore":4.5989,"artScore":23.932712067196814,"link":"http://www.litres.ru/sergey-tarmashev/odin-v-pole-ne-voin/","thumbnail":"http://cv8.litres.ru/static/bookimages/11/81/71/11817180.bin.dir/11817180.cover_89.jpg"},{"id":"node2754","bookName":"Те, кто выжил","price":79.9,"author":"Андрей Круз","year":null,"score":{"1":1,"2":3,"3":3,"4":16,"5":126},"avgScore":4.7651,"artScore":23.844307900108678,"link":"http://www.litres.ru/andrey-kruz/te-kto-vyzhil/","thumbnail":"http://cv5.litres.ru/static/bookimages/02/02/50/02025055.bin.dir/02025055.cover_89.jpg"},{"id":"node3105","bookName":"Начало","price":69.9,"author":"Алексей Калугин","year":null,"score":{"1":7,"2":7,"3":18,"4":54,"5":141},"avgScore":4.3877,"artScore":23.802864392592642,"link":"http://www.litres.ru/aleksey-kalugin/nachalo/","thumbnail":"http://cv3.litres.ru/static/bookimages/08/81/53/08815330.bin.dir/08815330.cover_89.jpg"},{"id":"node2389","bookName":"Государство в государстве","price":129.9,"author":"Сергей Тармашев","year":null,"score":{"1":7,"2":2,"3":7,"4":18,"5":138},"avgScore":4.6163,"artScore":23.762271011107046,"link":"http://www.litres.ru/sergey-tarmashev/gosudarstvo-v-gosudarstve/","thumbnail":"http://cv7.litres.ru/static/bookimages/07/99/52/07995278.bin.dir/07995278.cover_89.jpg"},{"id":"node2349","bookName":"Космопсихолухи. Том 2","price":99.9,"author":"Ольга Громыко","year":null,"score":{"1":6,"2":2,"3":4,"4":9,"5":135},"avgScore":4.6987,"artScore":23.727849056079016,"link":"http://www.litres.ru/olga-gromyko/kosmopsiholuhi-tom/6880372/","thumbnail":"http://cv8.litres.ru/static/bookimages/09/23/42/09234288.bin.dir/09234288.cover_89.jpg"},{"id":"node2390","bookName":"Заражение","price":99.9,"author":"Сергей Тармашев","year":null,"score":{"1":5,"2":1,"3":10,"4":25,"5":130},"avgScore":4.6023,"artScore":23.663679641612,"link":"http://www.litres.ru/sergey-tarmashev/zarazhenie/","thumbnail":"http://cv8.litres.ru/static/bookimages/01/77/72/01777285.bin.dir/01777285.cover_89.jpg"},{"id":"node2397","bookName":"Путь Шамана. Гамбит Картоса","price":69.9,"author":"Василий Маханенко","year":null,"score":{"1":3,"2":0,"3":3,"4":9,"5":122},"avgScore":4.8029,"artScore":23.63027335164399,"link":"http://www.litres.ru/vasiliy-mahanenko/put-shamana-gambit-kartosa/","thumbnail":"http://cv3.litres.ru/static/bookimages/08/43/00/08430030.bin.dir/08430030.cover_89.jpg"},{"id":"node2695","bookName":"Рай беспощадный","price":79.9,"author":"Артем Каменистый","year":null,"score":{"1":4,"2":3,"3":7,"4":30,"5":126},"avgScore":4.5941,"artScore":23.59446223108763,"link":"http://www.litres.ru/artem-kamenistyy/ray-besposchadnyy/","thumbnail":"http://cv4.litres.ru/static/bookimages/07/61/52/07615241.bin.dir/07615241.cover_89.jpg"},{"id":"node2396","bookName":"Цена алчности","price":99.9,"author":"Сергей Тармашев","year":null,"score":{"1":3,"2":5,"3":5,"4":21,"5":127},"avgScore":4.6398,"artScore":23.576453788776238,"link":"http://www.litres.ru/sergey-tarmashev/cena-alchnosti/","thumbnail":"http://cv3.litres.ru/static/bookimages/02/05/35/02053535.bin.dir/02053535.cover_89.jpg"},{"id":"node2379","bookName":"Нижний уровень","price":99.9,"author":"Андрей Круз","year":null,"score":{"1":4,"2":5,"3":16,"4":47,"5":125},"avgScore":4.4416,"artScore":23.4660064068215,"link":"http://www.litres.ru/andrey-kruz/nizhniy-uroven/","thumbnail":"http://cv3.litres.ru/static/bookimages/12/11/63/12116337.bin.dir/12116337.cover_89.jpg"},{"id":"node2698","bookName":"Красные камни Белого","price":139.9,"author":"Вадим Панов","year":null,"score":{"1":2,"2":2,"3":9,"4":33,"5":116},"avgScore":4.5988,"artScore":23.396662158436573,"link":"http://www.litres.ru/vadim-panov/krasnye-kamni-belogo/","thumbnail":"http://cv4.litres.ru/static/bookimages/05/83/19/05831945.bin.dir/05831945.cover_89.jpg"},{"id":"node2595","bookName":"Эпоха мёртвых. Начало","price":79.9,"author":"Андрей Круз","year":null,"score":{"1":6,"2":3,"3":7,"4":12,"5":129},"avgScore":4.6242,"artScore":23.381111173006868,"link":"http://www.litres.ru/andrey-kruz/epoha-mertvyh-nachalo/","thumbnail":"http://cv5.litres.ru/static/bookimages/09/35/63/09356359.bin.dir/09356359.cover_89.jpg"},{"id":"node2865","bookName":"Пересмешник","price":79.9,"author":"Алексей Пехов","year":null,"score":{"1":2,"2":0,"3":3,"4":12,"5":113},"avgScore":4.8,"artScore":23.364165362186792,"link":"http://www.litres.ru/aleksey-pehov/peresmeshnik/","thumbnail":"http://cv0.litres.ru/static/bookimages/00/83/95/00839502.bin.dir/00839502.cover_89.jpg"},{"id":"node2498","bookName":"Тринадцатая невеста","price":89.9,"author":"Милена Завойчинская","year":null,"score":{"1":2,"2":2,"3":12,"4":35,"5":115},"avgScore":4.5602,"artScore":23.311896114819284,"link":"http://www.litres.ru/milena-zavoychinskaya/trinadcataya-nevesta/","thumbnail":"http://cv4.litres.ru/static/bookimages/08/01/14/08011445.bin.dir/08011445.cover_89.jpg"},{"id":"node2404","bookName":"Обреченные","price":99.9,"author":"Сергей Тармашев","year":null,"score":{"1":2,"2":1,"3":6,"4":25,"5":112},"avgScore":4.6712,"artScore":23.279587092375277,"link":"http://www.litres.ru/sergey-tarmashev/obrechennye/","thumbnail":"http://cv6.litres.ru/static/bookimages/04/02/74/04027465.bin.dir/04027465.cover_89.jpg"},{"id":"node2399","bookName":"Путь Шамана. Тайна Темного леса","price":79.99,"author":"Василий Маханенко","year":null,"score":{"1":0,"2":0,"3":4,"4":12,"5":107},"avgScore":4.8374,"artScore":23.278452771254585,"link":"http://www.litres.ru/vasiliy-mahanenko/put-shamana-tayna-temnogo-lesa/","thumbnail":"http://cv7.litres.ru/static/bookimages/08/82/85/08828573.bin.dir/08828573.cover_89.jpg"},{"id":"node2592","bookName":"Последний адмирал Заграты","price":139.9,"author":"Вадим Панов","year":null,"score":{"1":5,"2":7,"3":18,"4":46,"5":125},"avgScore":4.3881,"artScore":23.271218549169543,"link":"http://www.litres.ru/vadim-panov/posledniy-admiral-zagraty/601015/","thumbnail":"http://cv6.litres.ru/static/bookimages/05/83/18/05831865.bin.dir/05831865.cover_89.jpg"},{"id":"node2633","bookName":"На переломе веков","price":119,"author":"Роман Злотников","year":null,"score":{"1":3,"2":2,"3":7,"4":23,"5":116},"avgScore":4.6358,"artScore":23.258913148770816,"link":"http://www.litres.ru/roman-zlotnikov/na-perelome-vekov/","thumbnail":"http://cv1.litres.ru/static/bookimages/04/69/75/04697515.bin.dir/04697515.cover_89.jpg"},{"id":"node2783","bookName":"Безымянный раб","price":89.9,"author":"Виталий Зыков","year":null,"score":{"1":2,"2":1,"3":1,"4":12,"5":110},"avgScore":4.8016,"artScore":23.221829788474277,"link":"http://www.litres.ru/vitaliy-zykov/bezymyannyy-rab/","thumbnail":"http://cv6.litres.ru/static/bookimages/04/42/13/04421365.bin.dir/04421365.cover_89.jpg"},{"id":"node2398","bookName":"Вычеркнутые из жизни","price":99.9,"author":"Сергей Тармашев","year":null,"score":{"1":3,"2":3,"3":2,"4":21,"5":114},"avgScore":4.6783,"artScore":23.217783618290817,"link":"http://www.litres.ru/sergey-tarmashev/vycherknutye-iz-zhizni/","thumbnail":"http://cv7.litres.ru/static/bookimages/05/19/76/05197675.bin.dir/05197675.cover_89.jpg"},{"id":"node2387","bookName":"Рождение победителя","price":89.9,"author":"Артем Каменистый","year":null,"score":{"1":3,"2":4,"3":10,"4":41,"5":113},"avgScore":4.5029,"artScore":23.15252010510126,"link":"http://www.litres.ru/artem-kamenistyy/rozhdenie-pobeditelya/","thumbnail":"http://cv1.litres.ru/static/bookimages/05/28/89/05288915.bin.dir/05288915.cover_89.jpg"},{"id":"node2313","bookName":"Застава","price":119,"author":"Сергей Лукьяненко","year":null,"score":{"1":40,"2":17,"3":64,"4":104,"5":166},"avgScore":3.867,"artScore":23.08103792638781,"link":"http://www.litres.ru/sergey-lukyanenko/zastava/","thumbnail":"http://cv8.litres.ru/static/bookimages/08/63/89/08638987.bin.dir/08638987.cover_89.jpg"},{"id":"node2465","bookName":"На границе тучи ходят хмуро…","price":69.9,"author":"Алексей Кулаков","year":null,"score":{"1":3,"2":3,"3":7,"4":19,"5":114},"avgScore":4.6301,"artScore":23.07478134284628,"link":"http://www.litres.ru/aleksey-kulakov/na-granice-tuchi-hodyat-hmuro/","thumbnail":"http://cv4.litres.ru/static/bookimages/04/42/43/04424345.bin.dir/04424345.cover_89.jpg"},{"id":"node2525","bookName":"Ловец человеков","price":109,"author":"Надежда Попова","year":null,"score":{"1":6,"2":1,"3":9,"4":11,"5":120},"avgScore":4.619,"artScore":23.05104575774033,"link":"http://www.litres.ru/nadezhda-popova/lovec-chelovekov/","thumbnail":"http://cv3.litres.ru/static/bookimages/07/01/64/07016432.bin.dir/07016432.cover_89.jpg"},{"id":"node2375","bookName":"Леди не движется – 2","price":99.9,"author":"Олег Дивов","year":null,"score":{"1":2,"2":11,"3":9,"4":27,"5":119},"avgScore":4.4881,"artScore":22.996838335643293,"link":"http://www.litres.ru/oleg-divov/ledi-ne-dvizhetsya-2/","thumbnail":"http://cv5.litres.ru/static/bookimages/08/42/44/08424459.bin.dir/08424459.cover_89.jpg"},{"id":"node2329","bookName":"Метро 2033","price":99.9,"author":"Дмитрий Глуховский","year":null,"score":{"1":18,"2":4,"3":17,"4":32,"5":141},"avgScore":4.2925,"artScore":22.99289391385504,"link":"http://www.litres.ru/dmitriy-gluhovskiy/metro-2033/","thumbnail":"http://cv5.litres.ru/static/bookimages/08/29/12/08291258.bin.dir/08291258.cover_89.jpg"},{"id":"node2510","bookName":"Катастрофа","price":119.9,"author":"Сергей Тармашев","year":null,"score":{"1":4,"2":9,"3":10,"4":22,"5":122},"avgScore":4.491,"artScore":22.985002151204494,"link":"http://www.litres.ru/sergey-tarmashev/katastrofa/","thumbnail":"http://cv0.litres.ru/static/bookimages/08/37/26/08372604.bin.dir/08372604.cover_89.jpg"},{"id":"node2691","bookName":"Эпоха мертвых. Прорыв","price":79.9,"author":"Андрей Круз","year":null,"score":{"1":1,"2":0,"3":5,"4":4,"5":105},"avgScore":4.8435,"artScore":22.981975608902932,"link":"http://www.litres.ru/andrey-kruz/epoha-mertvyh-proryv/","thumbnail":"http://cv9.litres.ru/static/bookimages/03/90/99/03909995.bin.dir/03909995.cover_89.jpg"},{"id":"node2487","bookName":"Алета","price":89.9,"author":"Милена Завойчинская","year":null,"score":{"1":0,"2":4,"3":9,"4":21,"5":107},"avgScore":4.6383,"artScore":22.95382246858001,"link":"http://www.litres.ru/milena-zavoychinskaya/aleta-2/","thumbnail":"http://cv7.litres.ru/static/bookimages/08/22/70/08227070.bin.dir/08227070.cover_89.jpg"},{"id":"node2810","bookName":"Я еду домой!","price":79.9,"author":"Андрей Круз","year":null,"score":{"1":3,"2":1,"3":8,"4":9,"5":111},"avgScore":4.697,"artScore":22.934372661958722,"link":"http://www.litres.ru/andrey-kruz/ya-edu-domoy/","thumbnail":"http://cv7.litres.ru/static/bookimages/02/02/47/02024775.bin.dir/02024775.cover_89.jpg"},{"id":"node2552","bookName":"Голодные игры","price":149.9,"author":"Сьюзен Коллинз","year":null,"score":{"1":7,"2":1,"3":10,"4":12,"5":118},"avgScore":4.5743,"artScore":22.858869656070535,"link":"http://www.litres.ru/suzen-kollinz/golodnye-igry/","thumbnail":"http://cv4.litres.ru/static/bookimages/08/72/68/08726848.bin.dir/08726848.cover_89.jpg"},{"id":"node2613","bookName":"Чужак. Охотник","price":89.9,"author":"Игорь Дравин","year":null,"score":{"1":2,"2":2,"3":2,"4":17,"5":103},"avgScore":4.7222,"artScore":22.837997892862806,"link":"http://www.litres.ru/igor-dravin/ohotnik/","thumbnail":"http://cv9.litres.ru/static/bookimages/07/97/46/07974696.bin.dir/07974696.cover_89.jpg"},{"id":"node2357","bookName":"Самый странный нуб","price":99.9,"author":"Артем Каменистый","year":null,"score":{"1":4,"2":2,"3":5,"4":21,"5":107},"avgScore":4.6187,"artScore":22.790879600026976,"link":"http://www.litres.ru/artem-kamenistyy/samyy-strannyy-nub/","thumbnail":"http://cv9.litres.ru/static/bookimages/12/36/55/12365599.bin.dir/12365599.cover_89.jpg"},{"id":"node2412","bookName":"Неотвратимая гибель","price":129.9,"author":"Сергей Тармашев","year":null,"score":{"1":10,"2":3,"3":13,"4":30,"5":119},"avgScore":4.4,"artScore":22.725058285263465,"link":"http://www.litres.ru/sergey-tarmashev/neotvratimaya-gibel/","thumbnail":"http://cv4.litres.ru/static/bookimages/07/13/48/07134840.bin.dir/07134840.cover_89.jpg"},{"id":"node2604","bookName":"Чужак. Ученик","price":89.9,"author":"Игорь Дравин","year":null,"score":{"1":8,"2":6,"3":5,"4":21,"5":118},"avgScore":4.4873,"artScore":22.717594166421627,"link":"http://www.litres.ru/igor-dravin/uchenik/","thumbnail":"http://cv9.litres.ru/static/bookimages/07/97/46/07974693.bin.dir/07974693.cover_89.jpg"},{"id":"node2562","bookName":"Час воздаяния","price":119.9,"author":"Сергей Тармашев","year":null,"score":{"1":3,"2":1,"3":4,"4":19,"5":102},"avgScore":4.6744,"artScore":22.716797514898172,"link":"http://www.litres.ru/sergey-tarmashev/chas-vozdayaniya/","thumbnail":"http://cv2.litres.ru/static/bookimages/05/80/69/05806925.bin.dir/05806925.cover_89.jpg"},{"id":"node2446","bookName":"Попала!","price":129,"author":"Надежда Кузьмина","year":null,"score":{"1":16,"2":8,"3":24,"4":35,"5":135},"avgScore":4.2156,"artScore":22.698857625596805,"link":"http://www.litres.ru/nadezhda-kuzmina/popala/","thumbnail":"http://cv1.litres.ru/static/bookimages/03/80/42/03804215.bin.dir/03804215.cover_89.jpg"},{"id":"node2358","bookName":"Элита элит","price":149,"author":"Роман Злотников","year":null,"score":{"1":7,"2":5,"3":3,"4":21,"5":113},"avgScore":4.5302,"artScore":22.66888427049006,"link":"http://www.litres.ru/roman-zlotnikov/elita-elit/","thumbnail":"http://cv3.litres.ru/static/bookimages/11/79/49/11794936.bin.dir/11794936.cover_89.jpg"},{"id":"node2361","bookName":"Дама с собачкой","price":99.9,"author":"Олег Дивов","year":null,"score":{"1":3,"2":0,"3":7,"4":19,"5":100},"avgScore":4.6512,"artScore":22.60377862154744,"link":"http://www.litres.ru/oleg-divov/dama-s-sobachkoy/","thumbnail":"http://cv4.litres.ru/static/bookimages/08/90/40/08904042.bin.dir/08904042.cover_89.jpg"},{"id":"node2623","bookName":"Земля лишних. Исход","price":89.9,"author":"Андрей Круз и др.","year":null,"score":{"1":2,"2":1,"3":9,"4":7,"5":103},"avgScore":4.7049,"artScore":22.60252523947298,"link":"http://www.litres.ru/andrey-kruz/mariya-kruz/zemlya-lishnih-ishod/","thumbnail":"http://cv9.litres.ru/static/bookimages/00/82/76/00827692.bin.dir/00827692.cover_89.jpg"},{"id":"node2694","bookName":"Чужак. Боевик-универсал","price":89.9,"author":"Игорь Дравин","year":null,"score":{"1":1,"2":2,"3":1,"4":14,"5":96},"avgScore":4.7719,"artScore":22.600806628276217,"link":"http://www.litres.ru/igor-dravin/boevik-universal/","thumbnail":"http://cv0.litres.ru/static/bookimages/07/97/47/07974705.bin.dir/07974705.cover_89.jpg"},{"id":"node2587","bookName":"Двери во Тьме","price":89.9,"author":"Андрей Круз и др.","year":null,"score":{"1":5,"2":5,"3":7,"4":38,"5":104},"avgScore":4.4528,"artScore":22.570969651726305,"link":"http://www.litres.ru/andrey-kruz/mariya-kruz/dveri-vo-tme/","thumbnail":"http://cv5.litres.ru/static/bookimages/04/85/58/04855855.bin.dir/04855855.cover_89.jpg"},{"id":"node2687","bookName":"Эпоха мертвых. Москва","price":79.9,"author":"Андрей Круз","year":null,"score":{"1":1,"2":5,"3":6,"4":7,"5":102},"avgScore":4.686,"artScore":22.472836687800545,"link":"http://www.litres.ru/andrey-kruz/epoha-mertvyh-moskva/","thumbnail":"http://cv2.litres.ru/static/bookimages/03/91/00/03910025.bin.dir/03910025.cover_89.jpg"},{"id":"node2580","bookName":"На пороге Тьмы","price":89.9,"author":"Андрей Круз и др.","year":null,"score":{"1":3,"2":2,"3":8,"4":20,"5":100},"avgScore":4.594,"artScore":22.466190353980547,"link":"http://www.litres.ru/andrey-kruz/mariya-kruz/na-poroge-tmy/","thumbnail":"http://cv2.litres.ru/static/bookimages/00/82/77/00827722.bin.dir/00827722.cover_89.jpg"},{"id":"node2635","bookName":"Взлет","price":119,"author":"Роман Злотников","year":null,"score":{"1":4,"2":2,"3":4,"4":23,"5":99},"avgScore":4.5985,"artScore":22.453490656798696,"link":"http://www.litres.ru/roman-zlotnikov/vzlet/","thumbnail":"http://cv5.litres.ru/static/bookimages/05/61/48/05614855.bin.dir/05614855.cover_89.jpg"},{"id":"node2607","bookName":"Ведьмины байки","price":89.9,"author":"Ольга Громыко","year":null,"score":{"1":1,"2":0,"3":4,"4":16,"5":91},"avgScore":4.75,"artScore":22.412869638651696,"link":"http://www.litres.ru/olga-gromyko/vedminy-bayki/","thumbnail":"http://cv1.litres.ru/static/bookimages/00/63/39/00633912.bin.dir/00633912.cover_89.jpg"},{"id":"node2649","bookName":"Чужак. Барон","price":89.9,"author":"Игорь Дравин","year":null,"score":{"1":2,"2":0,"3":3,"4":15,"5":92},"avgScore":4.7411,"artScore":22.37074018174742,"link":"http://www.litres.ru/igor-dravin/baron/","thumbnail":"http://cv9.litres.ru/static/bookimages/07/97/46/07974699.bin.dir/07974699.cover_89.jpg"},{"id":"node2576","bookName":"Возрождение","price":119.9,"author":"Сергей Тармашев","year":null,"score":{"1":6,"2":2,"3":3,"4":17,"5":102},"avgScore":4.5923,"artScore":22.353215897902164,"link":"http://www.litres.ru/sergey-tarmashev/vozrozhdenie/","thumbnail":"http://cv4.litres.ru/static/bookimages/04/80/89/04808945.bin.dir/04808945.cover_89.jpg"},{"id":"node2391","bookName":"Дом на перекрестке. Резиденция феи","price":99.9,"author":"Милена Завойчинская","year":null,"score":{"1":0,"2":2,"3":7,"4":16,"5":92},"avgScore":4.6923,"artScore":22.34558538489342,"link":"http://www.litres.ru/milena-zavoychinskaya/dom-na-perekrestke-rezidenciya-fei-2/","thumbnail":"http://cv7.litres.ru/static/bookimages/08/89/98/08899872.bin.dir/08899872.cover_89.jpg"},{"id":"node2386","bookName":"Дом на перекрестке. Под небом четырех миров","price":99.9,"author":"Милена Завойчинская","year":null,"score":{"1":6,"2":1,"3":11,"4":16,"5":104},"avgScore":4.529,"artScore":22.315460529389323,"link":"http://www.litres.ru/milena-zavoychinskaya/dom-na-perekrestke-pod-nebom-chetyreh-mirov-2/","thumbnail":"http://cv3.litres.ru/static/bookimages/08/91/19/08911934.bin.dir/08911934.cover_89.jpg"},{"id":"node2596","bookName":"Война","price":119.9,"author":"Сергей Тармашев","year":null,"score":{"1":1,"2":5,"3":4,"4":10,"5":97},"avgScore":4.6838,"artScore":22.304883041413138,"link":"http://www.litres.ru/sergey-tarmashev/voyna/","thumbnail":"http://cv3.litres.ru/static/bookimages/04/50/30/04503035.bin.dir/04503035.cover_89.jpg"},{"id":"node3377","bookName":"Дочь тысячи джеддаков","price":99.9,"author":"Эдгар Берроуз","year":null,"score":{"1":19,"2":17,"3":29,"4":40,"5":136},"avgScore":4.0664,"artScore":22.30332362725374,"link":"http://www.litres.ru/edgar-berrouz/doch-tysyachi-dzheddakov/","thumbnail":"http://cv2.litres.ru/static/bookimages/04/68/76/04687625.bin.dir/04687625.cover_89.jpg"},{"id":"node2773","bookName":"От чужих берегов","price":79.9,"author":"Андрей Круз","year":null,"score":{"1":1,"2":2,"3":2,"4":8,"5":91},"avgScore":4.7885,"artScore":22.239487187975698,"link":"http://www.litres.ru/andrey-kruz/ot-chuzhih-beregov/","thumbnail":"http://cv8.litres.ru/static/bookimages/02/02/47/02024785.bin.dir/02024785.cover_89.jpg"},{"id":"node2647","bookName":"Голодные игры. И вспыхнет пламя. Сойка-пересмешница (сборник)","price":249,"author":"Сьюзен Коллинз","year":null,"score":{"1":6,"2":3,"3":5,"4":12,"5":103},"avgScore":4.5736,"artScore":22.227048977045015,"link":"http://www.litres.ru/suzen-kollinz/golodnye-igry-i-vspyhnet-plamya-soyka-peresmeshnica/","thumbnail":"http://cv9.litres.ru/static/bookimages/08/90/42/08904295.bin.dir/08904295.cover_89.jpg"},{"id":"node2703","bookName":"Чужак. Мэтр","price":89.9,"author":"Игорь Дравин","year":null,"score":{"1":3,"2":3,"3":0,"4":18,"5":93},"avgScore":4.6667,"artScore":22.22347835921475,"link":"http://www.litres.ru/igor-dravin/metr/","thumbnail":"http://cv1.litres.ru/static/bookimages/07/97/47/07974714.bin.dir/07974714.cover_89.jpg"},{"id":"node2505","bookName":"Оружейникъ","price":69.9,"author":"Алексей Кулаков","year":null,"score":{"1":5,"2":4,"3":4,"4":17,"5":100},"avgScore":4.5615,"artScore":22.203445605995636,"link":"http://www.litres.ru/aleksey-kulakov/oruzheynik/","thumbnail":"http://cv3.litres.ru/static/bookimages/05/28/80/05288035.bin.dir/05288035.cover_89.jpg"},{"id":"node2645","bookName":"На краю архипелага","price":79.9,"author":"Артем Каменистый","year":null,"score":{"1":4,"2":4,"3":4,"4":27,"5":95},"avgScore":4.5299,"artScore":22.186483271596128,"link":"http://www.litres.ru/artem-kamenistyy/na-krau-arhipelaga/","thumbnail":"http://cv9.litres.ru/static/bookimages/07/61/57/07615791.bin.dir/07615791.cover_89.jpg"},{"id":"node2697","bookName":"Чужак. Рейнджер","price":89.9,"author":"Игорь Дравин","year":null,"score":{"1":1,"2":1,"3":4,"4":11,"5":89},"avgScore":4.7547,"artScore":22.1733330506339,"link":"http://www.litres.ru/igor-dravin/reyndzher/","thumbnail":"http://cv0.litres.ru/static/bookimages/07/97/47/07974702.bin.dir/07974702.cover_89.jpg"},{"id":"node2335","bookName":"Невеста воина, или Месть по расписанию","price":79.9,"author":"Елена Звёздная","year":null,"score":{"1":2,"2":0,"3":3,"4":11,"5":89},"avgScore":4.7619,"artScore":22.16171594892034,"link":"http://www.litres.ru/elena-zvezdnaya/nevesta-voina-ili-mest-po-raspisaniu-3/","thumbnail":"http://cv2.litres.ru/static/bookimages/08/81/10/08811022.bin.dir/08811022.cover_89.jpg"},{"id":"node2500","bookName":"Сосватать героя, или Невеста для злодея","price":99.9,"author":"Елена Звёздная","year":null,"score":{"1":3,"2":4,"3":7,"4":14,"5":97},"avgScore":4.584,"artScore":22.132990171793747,"link":"http://www.litres.ru/elena-zvezdnaya/sosvatat-geroya-ili-nevesta-dlya-zlodeya/","thumbnail":"http://cv2.litres.ru/static/bookimages/06/16/09/06160925.bin.dir/06160925.cover_89.jpg"},{"id":"node2411","bookName":"Дочь воина, или Кадеты не сдаются","price":79.9,"author":"Елена Звёздная","year":null,"score":{"1":2,"2":3,"3":4,"4":9,"5":93},"avgScore":4.6937,"artScore":22.105092202892724,"link":"http://www.litres.ru/elena-zvezdnaya/doch-voina-ili-kadety-ne-sdautsya/","thumbnail":"http://cv9.litres.ru/static/bookimages/08/60/86/08608696.bin.dir/08608696.cover_89.jpg"},{"id":"node2602","bookName":"Наследие","price":149,"author":"Сергей Тармашев","year":null,"score":{"1":4,"2":2,"3":4,"4":8,"5":96},"avgScore":4.6667,"artScore":22.102259422683517,"link":"http://www.litres.ru/sergey-tarmashev/nasledie/","thumbnail":"http://cv3.litres.ru/static/bookimages/07/08/76/07087632.bin.dir/07087632.cover_89.jpg"},{"id":"node2526","bookName":"Кардонийская петля","price":139.9,"author":"Вадим Панов","year":null,"score":{"1":4,"2":5,"3":6,"4":14,"5":99},"avgScore":4.5547,"artScore":22.09948159269638,"link":"http://www.litres.ru/vadim-panov/kardoniyskaya-petlya/","thumbnail":"http://cv3.litres.ru/static/bookimages/07/13/38/07133838.bin.dir/07133838.cover_89.jpg"},{"id":"node2599","bookName":"Война","price":119,"author":"Роман Злотников","year":null,"score":{"1":7,"2":4,"3":12,"4":30,"5":100},"avgScore":4.3856,"artScore":22.061593759667787,"link":"http://www.litres.ru/roman-zlotnikov/voyna/","thumbnail":"http://cv0.litres.ru/static/bookimages/05/83/56/05835605.bin.dir/05835605.cover_89.jpg"},{"id":"node2316","bookName":"451 градус по Фаренгейту","price":149.9,"author":"Рэй Брэдбери","year":null,"score":{"1":0,"2":1,"3":6,"4":10,"5":86},"avgScore":4.7573,"artScore":22.0487107188592,"link":"http://www.litres.ru/rey-bredberi/451-gradus-po-farengeytu/","thumbnail":"http://cv2.litres.ru/static/bookimages/08/45/60/08456025.bin.dir/08456025.cover_89.jpg"},{"id":"node2597","bookName":"Корпорация","price":119.9,"author":"Сергей Тармашев","year":null,"score":{"1":2,"2":4,"3":6,"4":11,"5":93},"avgScore":4.6293,"artScore":22.00584424282563,"link":"http://www.litres.ru/sergey-tarmashev/korporaciya/","thumbnail":"http://cv0.litres.ru/static/bookimages/04/50/17/04501705.bin.dir/04501705.cover_89.jpg"},{"id":"node2681","bookName":"Земля лишних. Новая жизнь","price":89.9,"author":"Андрей Круз и др.","year":null,"score":{"1":2,"2":1,"3":5,"4":9,"5":88},"avgScore":4.7143,"artScore":21.94009879227005,"link":"http://www.litres.ru/andrey-kruz/mariya-kruz/zemlya-lishnih-novaya-zhizn/","thumbnail":"http://cv0.litres.ru/static/bookimages/00/82/77/00827702.bin.dir/00827702.cover_89.jpg"},{"id":"node2632","bookName":"Сойка-пересмешница","price":149.9,"author":"Сьюзен Коллинз","year":null,"score":{"1":3,"2":2,"3":7,"4":9,"5":91},"avgScore":4.6339,"artScore":21.86518673192559,"link":"http://www.litres.ru/suzen-kollinz/soyka-peresmeshnica/","thumbnail":"http://cv8.litres.ru/static/bookimages/08/90/42/08904286.bin.dir/08904286.cover_89.jpg"},{"id":"node2543","bookName":"Vita Nostra","price":59.9,"author":"Марина и Сергей Дяченко","year":null,"score":{"1":2,"2":1,"3":8,"4":14,"5":87},"avgScore":4.6339,"artScore":21.86518673192559,"link":"http://www.litres.ru/marina-i-sergey-dyachenko/vita-nostra/","thumbnail":"http://cv8.litres.ru/static/bookimages/03/80/50/03805085.bin.dir/03805085.cover_89.jpg"},{"id":"node2469","bookName":"Головокружение","price":99.9,"author":"Вадим Панов","year":null,"score":{"1":12,"2":10,"3":24,"4":57,"5":102},"avgScore":4.1073,"artScore":21.863289767064558,"link":"http://www.litres.ru/vadim-panov/golovokruzhenie/","thumbnail":"http://cv6.litres.ru/static/bookimages/04/38/67/04386765.bin.dir/04386765.cover_89.jpg"},{"id":"node2407","bookName":"Понедельник начинается в субботу","price":59.9,"author":"Аркадий и Борис Стругацкие","year":null,"score":{"1":7,"2":3,"3":2,"4":7,"5":98},"avgScore":4.5897,"artScore":21.857157286940907,"link":"http://www.litres.ru/arkadiy-i-boris-strugackie/ponedelnik-nachinaetsya-v-subbotu/","thumbnail":"http://cv3.litres.ru/static/bookimages/01/63/35/01633535.bin.dir/01633535.cover_89.jpg"},{"id":"node2367","bookName":"Шаг к звездам","price":149.9,"author":"Роман Злотников","year":null,"score":{"1":3,"2":10,"3":12,"4":32,"5":92},"avgScore":4.3423,"artScore":21.728545367795956,"link":"http://www.litres.ru/roman-zlotnikov/shag-k-zvezdam/","thumbnail":"http://cv3.litres.ru/static/bookimages/08/21/38/08213837.bin.dir/08213837.cover_89.jpg"},{"id":"node2448","bookName":"Портрет Дориана Грея","price":79.99,"author":"Оскар Уайльд","year":null,"score":{"1":0,"2":2,"3":4,"4":13,"5":80},"avgScore":4.7273,"artScore":21.722384744837573,"link":"http://www.litres.ru/oskar-uayld/portret-doriana-greya/","thumbnail":"http://cv3.litres.ru/static/bookimages/11/17/69/11176931.bin.dir/11176931.cover_89.jpg"},{"id":"node2614","bookName":"Вторжение","price":119.9,"author":"Сергей Тармашев","year":null,"score":{"1":7,"2":4,"3":12,"4":17,"5":97},"avgScore":4.4088,"artScore":21.691010796650716,"link":"http://www.litres.ru/sergey-tarmashev/vtorzhenie/","thumbnail":"http://cv5.litres.ru/static/bookimages/04/06/88/04068855.bin.dir/04068855.cover_89.jpg"},{"id":"node2724","bookName":"Пастырь добрый","price":119.9,"author":"Надежда Попова","year":null,"score":{"1":1,"2":0,"3":0,"4":6,"5":78},"avgScore":4.8824,"artScore":21.690591427962843,"link":"http://www.litres.ru/nadezhda-popova/pastyr-dobryy/","thumbnail":"http://cv7.litres.ru/static/bookimages/08/38/12/08381273.bin.dir/08381273.cover_89.jpg"},{"id":"node2516","bookName":"Пограничная река","price":79.9,"author":"Артем Каменистый","year":null,"score":{"1":2,"2":1,"3":8,"4":21,"5":82},"avgScore":4.5789,"artScore":21.68680341960166,"link":"http://www.litres.ru/artem-kamenistyy/pogranichnaya-reka/","thumbnail":"http://cv1.litres.ru/static/bookimages/00/74/05/00740512.bin.dir/00740512.cover_89.jpg"},{"id":"node2533","bookName":"Возле Тьмы. Чужой","price":89.9,"author":"Андрей Круз и др.","year":null,"score":{"1":2,"2":1,"3":7,"4":26,"5":80},"avgScore":4.5603,"artScore":21.67801043768985,"link":"http://www.litres.ru/andrey-kruz/mariya-kruz/vozle-tmy-chuzhoy/","thumbnail":"http://cv7.litres.ru/static/bookimages/07/05/29/07052977.bin.dir/07052977.cover_89.jpg"},{"id":"node2351","bookName":"Настоящие индейцы","price":99.9,"author":"Олег Дивов","year":null,"score":{"1":3,"2":0,"3":8,"4":11,"5":84},"avgScore":4.6321,"artScore":21.601401838338965,"link":"http://www.litres.ru/oleg-divov/nastoyaschie-indeycy/","thumbnail":"http://cv5.litres.ru/static/bookimages/09/52/99/09529956.bin.dir/09529956.cover_89.jpg"},{"id":"node2583","bookName":"Магиня для эмиссара","price":79.99,"author":"Надежда Кузьмина","year":null,"score":{"1":3,"2":1,"3":1,"4":13,"5":81},"avgScore":4.697,"artScore":21.58313868557023,"link":"http://www.litres.ru/nadezhda-kuzmina/maginya-dlya-emissara-2/","thumbnail":"http://cv3.litres.ru/static/bookimages/07/99/93/07999335.bin.dir/07999335.cover_89.jpg"},{"id":"node2571","bookName":"Расплата","price":119.9,"author":"Сергей Тармашев","year":null,"score":{"1":4,"2":4,"3":2,"4":15,"5":85},"avgScore":4.5727,"artScore":21.49401476015952,"link":"http://www.litres.ru/sergey-tarmashev/rasplata/","thumbnail":"http://cv7.litres.ru/static/bookimages/04/70/15/04701575.bin.dir/04701575.cover_89.jpg"},{"id":"node2680","bookName":"Черные бушлаты","price":59.9,"author":"Александр Конторович","year":null,"score":{"1":2,"2":0,"3":7,"4":12,"5":79},"avgScore":4.66,"artScore":21.46009306670451,"link":"http://www.litres.ru/aleksandr-kontorovich/chernye-bushlaty-diversant-iz-buduschego/","thumbnail":"http://cv5.litres.ru/static/bookimages/10/81/64/10816456.bin.dir/10816456.cover_89.jpg"},{"id":"node2551","bookName":"Замуж с осложнениями","price":79.99,"author":"Юлия Жукова","year":null,"score":{"1":1,"2":2,"3":3,"4":10,"5":78},"avgScore":4.7234,"artScore":21.459817906293434,"link":"http://www.litres.ru/uliya-zhukova/zamuzh-s-oslozhneniyami/","thumbnail":"http://cv0.litres.ru/static/bookimages/04/42/59/04425905.bin.dir/04425905.cover_89.jpg"},{"id":"node2348","bookName":"Студёное дыхание","price":129.9,"author":"Сергей Тармашев","year":null,"score":{"1":4,"2":4,"3":7,"4":13,"5":86},"avgScore":4.5175,"artScore":21.39598421554988,"link":"http://www.litres.ru/sergey-tarmashev/studenoe-dyhanie/","thumbnail":"http://cv0.litres.ru/static/bookimages/11/34/69/11346900.bin.dir/11346900.cover_89.jpg"},{"id":"node2567","bookName":"Земли Хайтаны","price":79.9,"author":"Артем Каменистый","year":null,"score":{"1":1,"2":1,"3":3,"4":19,"5":73},"avgScore":4.6701,"artScore":21.36437188571499,"link":"http://www.litres.ru/artem-kamenistyy/zemli-haytany/","thumbnail":"http://cv5.litres.ru/static/bookimages/00/73/89/00738952.bin.dir/00738952.cover_89.jpg"},{"id":"node2728","bookName":"Вселенная неудачников","price":89.9,"author":"Роман Злотников и др.","year":null,"score":{"1":3,"2":4,"3":12,"4":35,"5":78},"avgScore":4.3712,"artScore":21.343762948451648,"link":"http://www.litres.ru/roman-zlotnikov/sergey-musanif/vselennaya-neudachnikov/","thumbnail":"http://cv6.litres.ru/static/bookimages/09/01/46/09014662.bin.dir/09014662.cover_89.jpg"},{"id":"node3497","bookName":"Один из леса","price":null,"author":"Андрей Левицкий","year":null,"score":{"1":6,"2":5,"3":9,"4":11,"5":91},"avgScore":4.4426,"artScore":21.34245414561494,"link":"http://www.litres.ru/andrey-levickiy/odin-iz-lesa/","thumbnail":"http://cv2.litres.ru/static/bookimages/11/77/20/11772021.bin.dir/11772021.cover_89.jpg"},{"id":"node3085","bookName":"Ник","price":59.9,"author":"Анджей Ясинский","year":null,"score":{"1":4,"2":4,"3":12,"4":18,"5":85},"avgScore":4.4309,"artScore":21.322280269266294,"link":"http://www.litres.ru/andzhey-yasinskiy/nik/","thumbnail":"http://cv7.litres.ru/static/bookimages/00/65/89/00658972.bin.dir/00658972.cover_89.jpg"},{"id":"node2383","bookName":"Ледяная бесконечность","price":129.9,"author":"Сергей Тармашев","year":null,"score":{"1":17,"2":7,"3":20,"4":27,"5":106},"avgScore":4.1186,"artScore":21.318718385968836,"link":"http://www.litres.ru/sergey-tarmashev/ledyanaya-beskonechnost/","thumbnail":"http://cv3.litres.ru/static/bookimages/08/85/48/08854839.bin.dir/08854839.cover_89.jpg"},{"id":"node2441","bookName":"Собачье сердце","price":39.9,"author":"Михаил Булгаков","year":null,"score":{"1":0,"2":0,"3":0,"4":5,"5":70},"avgScore":4.9333,"artScore":21.299608025339968,"link":"http://www.litres.ru/mihail-bulgakov/sobache-serdce/","thumbnail":"http://cv1.litres.ru/static/bookimages/08/25/75/08257510.bin.dir/08257510.cover_89.jpg"},{"id":"node2819","bookName":"Выбраковка","price":119,"author":"Олег Дивов","year":null,"score":{"1":1,"2":2,"3":4,"4":10,"5":76},"avgScore":4.6989,"artScore":21.2983438540959,"link":"http://www.litres.ru/oleg-divov/vybrakovka/","thumbnail":"http://cv2.litres.ru/static/bookimages/00/88/84/00888422.bin.dir/00888422.cover_89.jpg"},{"id":"node2560","bookName":"Четвертый год","price":79.9,"author":"Артем Каменистый","year":null,"score":{"1":1,"2":0,"3":3,"4":17,"5":71},"avgScore":4.7065,"artScore":21.28189623704319,"link":"http://www.litres.ru/artem-kamenistyy/chetvertyy-god/","thumbnail":"http://cv4.litres.ru/static/bookimages/00/73/89/00738942.bin.dir/00738942.cover_89.jpg"},{"id":"node2352","bookName":"Сердце для стража","price":89.9,"author":"Артем Каменистый","year":null,"score":{"1":5,"2":1,"3":7,"4":27,"5":78},"avgScore":4.4576,"artScore":21.265933153443797,"link":"http://www.litres.ru/artem-kamenistyy/serdce-dlya-strazha/","thumbnail":"http://cv9.litres.ru/static/bookimages/09/04/45/09044597.bin.dir/09044597.cover_89.jpg"},{"id":"node2734","bookName":"Земля лишних. За други своя","price":89.9,"author":"Андрей Круз и др.","year":null,"score":{"1":0,"2":2,"3":5,"4":4,"5":75},"avgScore":4.7674,"artScore":21.235841759136793,"link":"http://www.litres.ru/andrey-kruz/mariya-kruz/zemlya-lishnih-za-drugi-svoya/","thumbnail":"http://cv1.litres.ru/static/bookimages/00/82/77/00827712.bin.dir/00827712.cover_89.jpg"},{"id":"node2621","bookName":"Кардонийская рулетка","price":139.9,"author":"Вадим Панов","year":null,"score":{"1":5,"2":2,"3":9,"4":18,"5":82},"avgScore":4.4655,"artScore":21.227238955033954,"link":"http://www.litres.ru/vadim-panov/kardoniyskaya-ruletka/","thumbnail":"http://cv7.litres.ru/static/bookimages/05/83/19/05831975.bin.dir/05831975.cover_89.jpg"},{"id":"node2648","bookName":"Стезя смерти","price":109,"author":"Надежда Попова","year":null,"score":{"1":1,"2":0,"3":1,"4":8,"5":71},"avgScore":4.8272,"artScore":21.212711347932046,"link":"http://www.litres.ru/nadezhda-popova/stezya-smerti-2/","thumbnail":"http://cv1.litres.ru/static/bookimages/08/64/91/08649113.bin.dir/08649113.cover_89.jpg"},{"id":"node2757","bookName":"Замуж за Черного Властелина, или Мужики везде одинаковы","price":89.9,"author":"Юлия Славачевская и др.","year":null,"score":{"1":9,"2":6,"3":15,"4":34,"5":87},"avgScore":4.2185,"artScore":21.16561096543161,"link":"http://www.litres.ru/marina-rybickaya/uliya-slavachevskaya/zamuzh-za-chernogo-vlastelina-ili-muzhiki-vezde-odinakovy/","thumbnail":"http://cv9.litres.ru/static/bookimages/07/05/97/07059798.bin.dir/07059798.cover_89.jpg"},{"id":"node2569","bookName":"Пикник на обочине","price":59.9,"author":"Аркадий и Борис Стругацкие","year":null,"score":{"1":0,"2":2,"3":2,"4":9,"5":71},"avgScore":4.7738,"artScore":21.151875428986582,"link":"http://www.litres.ru/arkadiy-i-boris-strugackie/piknik-na-obochine/","thumbnail":"http://cv5.litres.ru/static/bookimages/06/39/66/06396657.bin.dir/06396657.cover_89.jpg"},{"id":"node2458","bookName":"Стратегия. Замок Россия","price":79.99,"author":"Вадим Денисов","year":null,"score":{"1":2,"2":1,"3":7,"4":13,"5":75},"avgScore":4.6122,"artScore":21.146992856409305,"link":"http://www.litres.ru/vadim-denisov/zamok-rossiya/","thumbnail":"http://cv9.litres.ru/static/bookimages/07/99/74/07997492.bin.dir/07997492.cover_89.jpg"},{"id":"node2532","bookName":"Дивизионный комиссар","price":89.9,"author":"Павел Корнев","year":null,"score":{"1":0,"2":1,"3":6,"4":19,"5":69},"avgScore":4.6421,"artScore":21.13957588555295,"link":"http://www.litres.ru/pavel-kornev/divizionnyy-komissar/","thumbnail":"http://cv3.litres.ru/static/bookimages/10/99/53/10995332.bin.dir/10995332.cover_89.jpg"},{"id":"node2322","bookName":"Марсианин","price":164,"author":"Энди Вейер","year":null,"score":{"1":6,"2":2,"3":8,"4":10,"5":84},"avgScore":4.4909,"artScore":21.109430002103686,"link":"http://www.litres.ru/endi-veyer/marsianin-2/","thumbnail":"http://cv1.litres.ru/static/bookimages/11/14/57/11145714.bin.dir/11145714.cover_89.jpg"},{"id":"node2983","bookName":"Основная миссия","price":59.9,"author":"Владислав Конюшевский","year":null,"score":{"1":2,"2":0,"3":3,"4":5,"5":73},"avgScore":4.7711,"artScore":21.08266121155791,"link":"http://www.litres.ru/vladislav-konushevskiy/osnovnaya-missiya/","thumbnail":"http://cv6.litres.ru/static/bookimages/00/30/89/00308962.bin.dir/00308962.cover_89.jpg"},{"id":"node2518","bookName":"Стратегия. Русский Союз","price":79.99,"author":"Вадим Денисов","year":null,"score":{"1":0,"2":0,"3":2,"4":13,"5":66},"avgScore":4.7901,"artScore":21.049953971995823,"link":"http://www.litres.ru/vadim-denisov/russkiy-souz/","thumbnail":"http://cv0.litres.ru/static/bookimages/07/99/75/07997507.bin.dir/07997507.cover_89.jpg"},{"id":"node2796","bookName":"Попытка возврата","price":59.9,"author":"Владислав Конюшевский","year":null,"score":{"1":0,"2":2,"3":0,"4":6,"5":69},"avgScore":4.8442,"artScore":21.04207041947141,"link":"http://www.litres.ru/vladislav-konushevskiy/popytka-vozvrata/","thumbnail":"http://cv6.litres.ru/static/bookimages/00/19/97/00199767.bin.dir/00199767.cover_89.jpg"},{"id":"node2864","bookName":"Лед","price":59.9,"author":"Павел Корнев","year":null,"score":{"1":3,"2":0,"3":16,"4":16,"5":76},"avgScore":4.4595,"artScore":21.00195900368846,"link":"http://www.litres.ru/pavel-kornev/led/","thumbnail":"http://cv7.litres.ru/static/bookimages/06/14/14/06141475.bin.dir/06141475.cover_89.jpg"},{"id":"node2744","bookName":"Наследие 2","price":149,"author":"Сергей Тармашев","year":null,"score":{"1":7,"2":6,"3":5,"4":19,"5":83},"avgScore":4.375,"artScore":20.94527637467145,"link":"http://www.litres.ru/sergey-tarmashev/nasledie/4602543/","thumbnail":"http://cv6.litres.ru/static/bookimages/07/98/18/07981863.bin.dir/07981863.cover_89.jpg"},{"id":"node2665","bookName":"Приключения Василисы, или Как Царевна-лягушка за счастьем ходила","price":69.9,"author":"Светлана Велесова","year":null,"score":{"1":2,"2":4,"3":12,"4":18,"5":75},"avgScore":4.4414,"artScore":20.917102603749672,"link":"http://www.litres.ru/svetlana-velesova/priklucheniya-vasilisy-ili-kak-carevna-lyagushka-za-schastem-hodila/","thumbnail":"http://cv2.litres.ru/static/bookimages/05/79/79/05797925.bin.dir/05797925.cover_89.jpg"},{"id":"node2779","bookName":"Под знаком мантикоры","price":79.9,"author":"Алексей Пехов","year":null,"score":{"1":0,"2":0,"3":3,"4":7,"5":66},"avgScore":4.8289,"artScore":20.912883365085527,"link":"http://www.litres.ru/aleksey-pehov/pod-znakom-mantikory/","thumbnail":"http://cv3.litres.ru/static/bookimages/08/16/12/08161237.bin.dir/08161237.cover_89.jpg"},{"id":"node2438","bookName":"Облачный атлас","price":149,"author":"Дэвид Митчелл","year":null,"score":{"1":17,"2":10,"3":20,"4":27,"5":100},"avgScore":4.0517,"artScore":20.903068879945263,"link":"http://www.litres.ru/devid-mitchell/oblachnyy-atlas/","thumbnail":"http://cv0.litres.ru/static/bookimages/08/37/28/08372806.bin.dir/08372806.cover_89.jpg"},{"id":"node2725","bookName":"Ведущий в погибель","price":119.9,"author":"Надежда Попова","year":null,"score":{"1":3,"2":0,"3":3,"4":6,"5":72},"avgScore":4.7143,"artScore":20.888136336138242,"link":"http://www.litres.ru/nadezhda-popova/veduschiy-v-pogibel/","thumbnail":"http://cv6.litres.ru/static/bookimages/08/78/48/08784869.bin.dir/08784869.cover_89.jpg"},{"id":"node3256","bookName":"Случай из практики","price":69.9,"author":"Кира Измайлова","year":null,"score":{"1":1,"2":3,"3":5,"4":11,"5":71},"avgScore":4.6264,"artScore":20.86892145154093,"link":"http://www.litres.ru/kira-izmaylova/sluchay-iz-praktiki/","thumbnail":"http://cv0.litres.ru/static/bookimages/01/28/39/01283905.bin.dir/01283905.cover_89.jpg"},{"id":"node2517","bookName":"Еще один шанс…","price":119,"author":"Роман Злотников","year":null,"score":{"1":2,"2":2,"3":4,"4":12,"5":71},"avgScore":4.6264,"artScore":20.86892145154093,"link":"http://www.litres.ru/roman-zlotnikov/esche-odin-shans/","thumbnail":"http://cv2.litres.ru/static/bookimages/07/10/26/07102626.bin.dir/07102626.cover_89.jpg"},{"id":"node2459","bookName":"Под Куполом","price":189.9,"author":"Стивен Кинг","year":null,"score":{"1":5,"2":2,"3":5,"4":13,"5":76},"avgScore":4.5149,"artScore":20.83658371891473,"link":"http://www.litres.ru/stiven-king/pod-kupolom/","thumbnail":"http://cv7.litres.ru/static/bookimages/06/35/76/06357675.bin.dir/06357675.cover_89.jpg"},{"id":"node2422","bookName":"Одиночка. Дорога мечей","price":89.9,"author":"Алекс Кош","year":null,"score":{"1":0,"2":0,"3":2,"4":13,"5":63},"avgScore":4.7821,"artScore":20.834005029971678,"link":"http://www.litres.ru/aleks-kosh/odinochka-doroga-mechey-2/","thumbnail":"http://cv6.litres.ru/static/bookimages/11/31/13/11311369.bin.dir/11311369.cover_89.jpg"},{"id":"node2514","bookName":"Стратегия. Спасатель","price":79.99,"author":"Вадим Денисов","year":null,"score":{"1":0,"2":0,"3":3,"4":11,"5":64},"avgScore":4.7821,"artScore":20.834005029971678,"link":"http://www.litres.ru/vadim-denisov/spasatel/","thumbnail":"http://cv0.litres.ru/static/bookimages/07/99/75/07997501.bin.dir/07997501.cover_89.jpg"},{"id":"node2969","bookName":"Лед. Чистильщик","price":69.9,"author":"Павел Корнев","year":null,"score":{"1":1,"2":0,"3":3,"4":18,"5":64},"avgScore":4.6744,"artScore":20.821483870284496,"link":"http://www.litres.ru/pavel-kornev/led-chistilschik/","thumbnail":"http://cv6.litres.ru/static/bookimages/07/13/42/07134260.bin.dir/07134260.cover_89.jpg"},{"id":"node2663","bookName":"Пересекая границы","price":59.9,"author":"Оксана Панкеева","year":null,"score":{"1":4,"2":1,"3":4,"4":7,"5":74},"avgScore":4.6222,"artScore":20.799120252971047,"link":"http://www.litres.ru/oksana-pankeeva/peresekaya-granicy/","thumbnail":"http://cv4.litres.ru/static/bookimages/02/03/21/02032145.bin.dir/02032145.cover_89.jpg"},{"id":"node2746","bookName":"Рейтар","price":99.9,"author":"Андрей Круз","year":null,"score":{"1":6,"2":9,"3":14,"4":32,"5":79},"avgScore":4.2071,"artScore":20.79019562012891,"link":"http://www.litres.ru/andrey-kruz/reytar/","thumbnail":"http://cv3.litres.ru/static/bookimages/07/10/02/07100238.bin.dir/07100238.cover_89.jpg"},{"id":"node2371","bookName":"Войны начинают неудачники","price":99.9,"author":"Вадим Панов","year":null,"score":{"1":1,"2":4,"3":11,"4":21,"5":70},"avgScore":4.4486,"artScore":20.787537614797312,"link":"http://www.litres.ru/vadim-panov/voyny-nachinaut-neudachniki/","thumbnail":"http://cv9.litres.ru/static/bookimages/00/88/72/00887292.bin.dir/00887292.cover_89.jpg"},{"id":"node2336","bookName":"Уши не трогать!","price":89.9,"author":"Анна Гаврилова","year":null,"score":{"1":13,"2":10,"3":16,"4":40,"5":86},"avgScore":4.0667,"artScore":20.76417825712506,"link":"http://www.litres.ru/anna-gavrilova/ushi-ne-trogat/","thumbnail":"http://cv9.litres.ru/static/bookimages/08/72/27/08722793.bin.dir/08722793.cover_89.jpg"},{"id":"node2432","bookName":"Без гнева и пристрастия","price":89.9,"author":"Павел Корнев","year":null,"score":{"1":0,"2":0,"3":1,"4":6,"5":63},"avgScore":4.8857,"artScore":20.756933893835086,"link":"http://www.litres.ru/pavel-kornev/bez-gneva-i-pristrastiya/","thumbnail":"http://cv4.litres.ru/static/bookimages/10/99/56/10995641.bin.dir/10995641.cover_89.jpg"},{"id":"node2486","bookName":"Стратегия. Экспансия","price":79.99,"author":"Вадим Денисов","year":null,"score":{"1":1,"2":0,"3":1,"4":13,"5":63},"avgScore":4.7564,"artScore":20.7222945456721,"link":"http://www.litres.ru/vadim-denisov/ekspansiya/","thumbnail":"http://cv9.litres.ru/static/bookimages/07/99/74/07997498.bin.dir/07997498.cover_89.jpg"},{"id":"node2934","bookName":"По эту сторону фронта","price":59.9,"author":"Владислав Конюшевский","year":null,"score":{"1":1,"2":1,"3":3,"4":3,"5":67},"avgScore":4.7867,"artScore":20.66637643391548,"link":"http://www.litres.ru/vladislav-konushevskiy/po-etu-storonu-fronta/","thumbnail":"http://cv7.litres.ru/static/bookimages/00/30/89/00308972.bin.dir/00308972.cover_89.jpg"},{"id":"node2368","bookName":"Исчадия техно","price":89.9,"author":"Артем Каменистый","year":null,"score":{"1":3,"2":1,"3":8,"4":19,"5":68},"avgScore":4.4949,"artScore":20.65483164523183,"link":"http://www.litres.ru/artem-kamenistyy/ischadiya-tehno/","thumbnail":"http://cv9.litres.ru/static/bookimages/08/99/12/08991292.bin.dir/08991292.cover_89.jpg"},{"id":"node2917","bookName":"Все зависит от нас","price":59.9,"author":"Владислав Конюшевский","year":null,"score":{"1":2,"2":0,"3":2,"4":1,"5":67},"avgScore":4.8194,"artScore":20.61115476613497,"link":"http://www.litres.ru/vladislav-konushevskiy/vse-zavisit-ot-nas/","thumbnail":"http://cv6.litres.ru/static/bookimages/00/63/64/00636462.bin.dir/00636462.cover_89.jpg"},{"id":"node2643","bookName":"Академия Ранмарн","price":99.9,"author":"Елена Звёздная","year":null,"score":{"1":7,"2":0,"3":8,"4":16,"5":74},"avgScore":4.4286,"artScore":20.61039583375248,"link":"http://www.litres.ru/elena-zvezdnaya/akademiya-ranmarn/","thumbnail":"http://cv7.litres.ru/static/bookimages/04/46/11/04461175.bin.dir/04461175.cover_89.jpg"},{"id":"node2570","bookName":"Это наш дом","price":79.9,"author":"Артем Каменистый","year":null,"score":{"1":2,"2":0,"3":2,"4":16,"5":63},"avgScore":4.6627,"artScore":20.603509820084856,"link":"http://www.litres.ru/artem-kamenistyy/eto-nash-dom/","thumbnail":"http://cv7.litres.ru/static/bookimages/00/73/89/00738972.bin.dir/00738972.cover_89.jpg"},{"id":"node2618","bookName":"Природа зверя","price":119,"author":"Надежда Попова","year":null,"score":{"1":6,"2":2,"3":1,"4":8,"5":74},"avgScore":4.5604,"artScore":20.571502143121517,"link":"http://www.litres.ru/nadezhda-popova/priroda-zverya/","thumbnail":"http://cv8.litres.ru/static/bookimages/11/04/68/11046882.bin.dir/11046882.cover_89.jpg"},{"id":"node3225","bookName":"Стихийник","price":59.9,"author":"Анджей Ясинский","year":null,"score":{"1":3,"2":1,"3":8,"4":18,"5":67},"avgScore":4.4948,"artScore":20.562618415066993,"link":"http://www.litres.ru/andzhey-yasinskiy/stihiynik/","thumbnail":"http://cv4.litres.ru/static/bookimages/01/27/92/01279245.bin.dir/01279245.cover_89.jpg"},{"id":"node2540","bookName":"Изольда Великолепная","price":69.9,"author":"Карина Демина","year":null,"score":{"1":0,"2":3,"3":3,"4":18,"5":62},"avgScore":4.6163,"artScore":20.56251018975181,"link":"http://www.litres.ru/karina-demina/izolda-velikolepnaya/","thumbnail":"http://cv5.litres.ru/static/bookimages/07/99/65/07996551.bin.dir/07996551.cover_89.jpg"},{"id":"node2742","bookName":"Черный снег","price":59.9,"author":"Александр Конторович","year":null,"score":{"1":1,"2":1,"3":5,"4":9,"5":65},"avgScore":4.679,"artScore":20.56168184418716,"link":"http://www.litres.ru/aleksandr-kontorovich/chernyy-sneg-vystrel-v-buduschee/","thumbnail":"http://cv9.litres.ru/static/bookimages/10/85/16/10851698.bin.dir/10851698.cover_89.jpg"},{"id":"node2608","bookName":"Волчонок","price":79.99,"author":"Генри Лайон Олди","year":null,"score":{"1":2,"2":1,"3":7,"4":10,"5":67},"avgScore":4.5977,"artScore":20.532910888466606,"link":"http://www.litres.ru/genri-oldi/volchonok/","thumbnail":"http://cv7.litres.ru/static/bookimages/08/22/71/08227178.bin.dir/08227178.cover_89.jpg"},{"id":"node2370","bookName":"Холод юга","price":89.9,"author":"Артем Каменистый","year":null,"score":{"1":1,"2":1,"3":6,"4":18,"5":62},"avgScore":4.5795,"artScore":20.504167454770514,"link":"http://www.litres.ru/artem-kamenistyy/holod-uga/","thumbnail":"http://cv0.litres.ru/static/bookimages/08/97/30/08973009.bin.dir/08973009.cover_89.jpg"}]